bitcoinrpc/__init__.py
bitcoinrpc/__version__.py
bitcoinrpc/_exceptions.py
bitcoinrpc/_spec.py
bitcoinrpc/_types.py
bitcoinrpc/bitcoin_rpc.py
bitcoinrpc-0.7.0.dist-info/LICENSE
bitcoinrpc-0.7.0.dist-info/METADATA
bitcoinrpc-0.7.0.dist-info/WHEEL
bitcoinrpc-0.7.0.dist-info/top_level.txt
bitcoinrpc-0.7.0.dist-info/RECORD
