Metadata-Version: 2.1
Name: bitcoinrpc
Version: 0.7.0
Summary: Lightweight Bitcoin JSON-RPC Python asynchronous client
Home-page: https://github.com/bibajz/bitcoin-python-async-rpc
Author: Libor Martinek
Author-email: libasmartinek@protonmail.com
License: MIT
Keywords: bitcoin async json-rpc
Classifier: Development Status :: 4 - Beta
Classifier: Intended Audience :: Developers
Classifier: Programming Language :: Python
Classifier: Programming Language :: Python :: 3.7
Classifier: Programming Language :: Python :: 3.8
Classifier: Programming Language :: Python :: 3.9
Classifier: Programming Language :: Python :: 3.10
Classifier: Programming Language :: Python :: 3.11
Classifier: Programming Language :: Python :: 3 :: Only
Classifier: Topic :: Software Development :: Libraries :: Python Modules
Requires-Python: >=3.7
License-File: LICENSE
Requires-Dist: orjson>=3
Requires-Dist: httpx<1
Requires-Dist: typing_extensions>=4.0.0
